hamkit/repeaterbook/__about__.py
hamkit/repeaterbook/__init__.py
hamkit/repeaterbook/_common.py
hamkit/repeaterbook/_repeaterbook.py
hamkit_repeaterbook-0.0.1a1.dist-info/METADATA
hamkit_repeaterbook-0.0.1a1.dist-info/WHEEL
hamkit_repeaterbook-0.0.1a1.dist-info/licenses/LICENSE
hamkit_repeaterbook-0.0.1a1.dist-info/RECORD
