Metadata-Version: 2.3
Name: hamkit-repeaterbook
Version: 0.0.1a1
Summary: A tool for working with local copies of the RepeaterBook database. Visit https://www.repeaterbook.com/wiki/doku.php?id=api for terms of use. In particular: "Use of the (RepeaterBook) data is for personal use only. The data cannot be fed to a commercial product for sale or otherwise."
Project-URL: Documentation, https://github.com/afourney/hamkit/blob/main/packages/repeaterbook/README.md
Project-URL: Issues, https://github.com/afourney/hamkit/issues
Project-URL: Source, https://github.com/afourney/hamkit/blob/main/packages/repeaterbook/README.md
Author-email: Adam Fourney <adam.fourney@gmail.com>
License-Expression: MIT
License-File: LICENSE
Classifier: Development Status :: 4 - Beta
Classifier: Programming Language :: Python
Classifier: Programming Language :: Python :: 3.10
Classifier: Programming Language :: Python :: 3.11
Classifier: Programming Language :: Python :: 3.12
Classifier: Programming Language :: Python :: Implementation :: CPython
Classifier: Programming Language :: Python :: Implementation :: PyPy
Requires-Python: >=3.10
Requires-Dist: haversine
Requires-Dist: requests
